{
  "apps": [
    {
      "Info": "",
      "Name": "1password-cli",
      "Source": "main",
      "Updated": "2023-07-12T02:22:09.9384254+09:00",
      "Version": "2.19.0"
    },
    {
      "Info": "",
      "Name": "7zip",
      "Source": "main",
      "Updated": "2023-07-12T02:22:15.5868256+09:00",
      "Version": "23.01"
    },
    {
      "Info": "",
      "Name": "aria2",
      "Source": "main",
      "Updated": "2023-04-23T05:56:26.9685744+09:00",
      "Version": "1.36.0-1"
    },
    {
      "Info": "",
      "Name": "bfg",
      "Source": "main",
      "Updated": "2022-11-15T16:37:25.0128306+09:00",
      "Version": "1.14.0"
    },
    {
      "Info": "",
      "Name": "chezmoi",
      "Source": "main",
      "Updated": "2023-07-24T01:09:45.7445742+09:00",
      "Version": "2.35.2"
    },
    {
      "Info": "",
      "Name": "fnm",
      "Source": "main",
      "Updated": "2023-07-24T01:09:48.5402767+09:00",
      "Version": "1.35.0"
    },
    {
      "Info": "",
      "Name": "fzf",
      "Source": "main",
      "Updated": "2023-06-24T20:31:40.991045+09:00",
      "Version": "0.42.0"
    },
    {
      "Info": "",
      "Name": "gh",
      "Source": "main",
      "Updated": "2023-07-30T07:13:12.2171378+09:00",
      "Version": "2.32.1"
    },
    {
      "Info": "",
      "Name": "ghq",
      "Source": "main",
      "Updated": "2023-04-23T05:09:16.7475273+09:00",
      "Version": "1.4.2"
    },
    {
      "Info": "",
      "Name": "git",
      "Source": "main",
      "Updated": "2023-07-24T01:10:04.6744569+09:00",
      "Version": "2.41.0.3"
    },
    {
      "Info": "",
      "Name": "jpegview",
      "Source": "extras",
      "Updated": "2023-04-23T22:57:55.3199031+09:00",
      "Version": "1.0.37"
    },
    {
      "Info": "",
      "Name": "ngrok",
      "Source": "main",
      "Updated": "2023-07-30T07:13:15.2529622+09:00",
      "Version": "3.3.2"
    },
    {
      "Info": "",
      "Name": "npiperelay",
      "Source": "extras",
      "Updated": "2022-11-15T16:37:32.5690634+09:00",
      "Version": "0.1.0"
    },
    {
      "Info": "",
      "Name": "nu",
      "Source": "main",
      "Updated": "2023-08-10T00:09:56.9158284+09:00",
      "Version": "0.83.1"
    },
    {
      "Info": "",
      "Name": "oh-my-posh",
      "Source": "https://github.com/JanDeDobbeleer/oh-my-posh/releases/latest/download/oh-my-posh.json",
      "Updated": "2023-08-10T00:10:11.2574116+09:00",
      "Version": "18.3.3"
    },
    {
      "Info": "",
      "Name": "pandoc",
      "Source": "main",
      "Updated": "2023-08-10T00:10:14.9489794+09:00",
      "Version": "3.1.6.1"
    },
    {
      "Info": "",
      "Name": "posh-git",
      "Source": "extras",
      "Updated": "2022-11-15T16:37:40.976872+09:00",
      "Version": "1.1.0"
    },
    {
      "Info": "",
      "Name": "sudo",
      "Source": "main",
      "Updated": "2022-11-15T16:37:41.3056599+09:00",
      "Version": "0.2020.01.26"
    },
    {
      "Info": "",
      "Name": "wezterm",
      "Source": "extras",
      "Updated": "2023-07-24T01:10:21.6648772+09:00",
      "Version": "20230712-072601-f4abf8fd"
    },
    {
      "Info": "",
      "Name": "zoxide",
      "Source": "main",
      "Updated": "2023-08-10T00:10:16.2829558+09:00",
      "Version": "0.9.2"
    }
  ],
  "buckets": [
    {
      "Manifests": 1888,
      "Name": "extras",
      "Source": "https://github.com/lukesampson/scoop-extras",
      "Updated": "2023-08-09T21:30:29+09:00"
    },
    {
      "Manifests": 0,
      "Name": "github-gh",
      "Source": "https://github.com/cli/scoop-gh.git",
      "Updated": "2023-05-04T21:33:48+09:00"
    },
    {
      "Manifests": 1217,
      "Name": "main",
      "Source": "https://github.com/ScoopInstaller/Main",
      "Updated": "2023-08-09T21:30:19+09:00"
    }
  ]
}
